lrux/__init__.py
lrux/det_lru.py
lrux/pf_lru.py
lrux/pfaffian.py
lrux-0.1.2.dist-info/licenses/LICENSE
lrux-0.1.2.dist-info/METADATA
lrux-0.1.2.dist-info/WHEEL
lrux-0.1.2.dist-info/top_level.txt
lrux-0.1.2.dist-info/RECORD
