Metadata-Version: 2.4
Name: lrux
Version: 0.1.2
Summary: Fast low-rank updates (LRU) of matrix determinants and pfaffians in JAX
Author-email: Ao Chen <chenao.phys@gmail.com>, Christopher Roth <christopher_roth@utexas.edu>
Requires-Python: >=3.8
License-File: LICENSE
Requires-Dist: jax>=0.4.4
Dynamic: license-file
